mock_aerohive/MockAerohive.py
mock_aerohive/__init__.py
mock_aerohive-0.0.2.dist-info/DESCRIPTION.rst
mock_aerohive-0.0.2.dist-info/METADATA
mock_aerohive-0.0.2.dist-info/RECORD
mock_aerohive-0.0.2.dist-info/WHEEL
mock_aerohive-0.0.2.dist-info/metadata.json
mock_aerohive-0.0.2.dist-info/top_level.txt
