Metadata-Version: 2.0
Name: mock-aerohive
Version: 0.0.2
Summary: A mock SSH server emulating Aerohive devices
Home-page: https://github.com/pencot/mock_aerohive
Author: Ryan Leonard
Author-email: UNKNOWN
License: MIT
Keywords: aerohive ssh mock server
Platform: UNKNOWN
Classifier: Development Status :: 3 - Alpha
Classifier: Framework :: Pytest
Classifier: Intended Audience :: Developers
Classifier: License :: OSI Approved :: MIT License
Classifier: Natural Language :: English
Classifier: Programming Language :: Python :: 2.7
Classifier: Topic :: Internet
Classifier: Topic :: Software Development :: Testing :: Mocking
Requires-Dist: mockssh (>=1.4.5,<2)
